{
  "id": "getting-started-guide",
  "title": "API Getting Started Guide",
  "description": "This is a template used for creating getting started with your API guides.",
  "source": "@site/docs/getting-started-guide.md",
  "sourceDirName": ".",
  "slug": "/getting-started-guide",
  "permalink": "/api-reference-sample/docs/getting-started-guide",
  "draft": false,
  "unlisted": false,
  "tags": [],
  "version": "current",
  "sidebarPosition": 3,
  "frontMatter": {
    "sidebar_label": "Getting Started Guide",
    "sidebar_position": 3
  },
  "sidebar": "tutorialSidebar",
  "previous": {
    "title": "Hello!",
    "permalink": "/api-reference-sample/docs/hello"
  },
  "next": {
    "title": "Authentication",
    "permalink": "/api-reference-sample/docs/authentication"
  }
}